taobao_open/__init__.py
taobao_open/api/__init__.py
taobao_open/api/base.py
taobao_open/api/rest/AppipGetRequest.py
taobao_open/api/rest/AreasGetRequest.py
taobao_open/api/rest/BaichuanOpenaccountLoginRequest.py
taobao_open/api/rest/BaichuanOpenaccountLoginbytokenRequest.py
taobao_open/api/rest/BaichuanOpenaccountLogindoublecheckRequest.py
taobao_open/api/rest/BaichuanOpenaccountNewlogindoublecheckRequest.py
taobao_open/api/rest/BaichuanOpenaccountPasswordResetRequest.py
taobao_open/api/rest/BaichuanOpenaccountRegisterRequest.py
taobao_open/api/rest/BaichuanOpenaccountRegistercodeCheckRequest.py
taobao_open/api/rest/BaichuanOpenaccountRegistercodeSendRequest.py
taobao_open/api/rest/BaichuanOpenaccountResetcodeCheckRequest.py
taobao_open/api/rest/BaichuanOpenaccountResetcodeSendRequest.py
taobao_open/api/rest/BaichuanOrderurlGetRequest.py
taobao_open/api/rest/BaichuanPayresultQueryRequest.py
taobao_open/api/rest/BaichuanTaokeTraceRequest.py
taobao_open/api/rest/BaichuanUserLoginRequest.py
taobao_open/api/rest/BaichuanUserLoginbytokenRequest.py
taobao_open/api/rest/BaichuanUserLogindoublecheckRequest.py
taobao_open/api/rest/CloudpushMessageAndroidRequest.py
taobao_open/api/rest/CloudpushMessageIosRequest.py
taobao_open/api/rest/CloudpushNoticeAndroidRequest.py
taobao_open/api/rest/CloudpushNoticeIosRequest.py
taobao_open/api/rest/CloudpushPushRequest.py
taobao_open/api/rest/DeliverySendRequest.py
taobao_open/api/rest/FilesGetRequest.py
taobao_open/api/rest/HttpdnsGetRequest.py
taobao_open/api/rest/ItemAddRequest.py
taobao_open/api/rest/ItemImgDeleteRequest.py
taobao_open/api/rest/ItemImgUploadRequest.py
taobao_open/api/rest/ItemJointImgRequest.py
taobao_open/api/rest/ItemJointPropimgRequest.py
taobao_open/api/rest/ItemSkusGetRequest.py
taobao_open/api/rest/ItemUpdateDelistingRequest.py
taobao_open/api/rest/ItemUpdateListingRequest.py
taobao_open/api/rest/ItemUpdateRequest.py
taobao_open/api/rest/ItempropvaluesGetRequest.py
taobao_open/api/rest/JuItemsSearchRequest.py
py_taobao_open-1.0.3.dist-info/LICENSE
py_taobao_open-1.0.3.dist-info/METADATA
py_taobao_open-1.0.3.dist-info/WHEEL
py_taobao_open-1.0.3.dist-info/top_level.txt
py_taobao_open-1.0.3.dist-info/RECORD
