Metadata-Version: 2.1
Name: py-taobao-open
Version: 1.0.3
Summary: 淘宝开放平台Python 3 SDK，基于官方SDK Python版本修改
Home-page: https://gitee.com/327630285/py_taobao_open
Author: tangzk
Author-email: tangzk@yeah.net
License: UNKNOWN
Platform: UNKNOWN
Classifier: License :: OSI Approved :: MIT License
Classifier: Operating System :: OS Independent
Classifier: Programming Language :: Python
Classifier: Programming Language :: Python :: Implementation
Classifier: Topic :: Software Development :: Libraries
License-File: LICENSE
